killbill/__init__.py
killbill/enums.py
killbill/exceptions.py
killbill/header.py
killbill/killbill.py
killbill/clients/__init__.py
killbill/clients/account.py
killbill/clients/base.py
killbill/clients/bundle.py
killbill/clients/catalog.py
killbill/clients/credit.py
killbill/clients/invoice.py
killbill/clients/overdue.py
killbill/clients/subscription.py
killbill/clients/tenant.py
killbill/clients/test.py
python_killbill_client-0.3.8.dist-info/METADATA
python_killbill_client-0.3.8.dist-info/WHEEL
python_killbill_client-0.3.8.dist-info/licenses/LICENSE
python_killbill_client-0.3.8.dist-info/RECORD
