Metadata-Version: 2.4
Name: python-killbill-client
Version: 0.3.8
Summary: killbill client
Project-URL: Homepage, https://github.com/raulodev/python-killbill-client
Project-URL: Issues, https://github.com/raulodev/python-killbill-client/issues
Author-email: Raul Cobiellas <raulodev@gmail.com>
License-File: LICENSE
Keywords: bill,kill,killbill
Classifier: License :: OSI Approved :: MIT License
Classifier: Operating System :: OS Independent
Classifier: Programming Language :: Python :: 3
Requires-Python: >=3.8
Requires-Dist: requests>=2.32.3
